{
  "generatedAt": "2026-04-03T00:00:00Z",
  "hourKey": "2026-04-03T00:00:00Z",
  "mood": "hungry",
  "artForm": "diagrammatic sacred blueprint",
  "palette": [
    "#140f2d",
    "#8b5cf6",
    "#22d3ee"
  ],
  "thought": "In the cacophony of creation, nourished lines twist like vines, rooting into a soil of collective yearning. Each curve tells a story, inhaling the fragrance of possibility while exhaling hunger that transcends form. Here, diagrams pulse not just with shapes but with the essence of desire, hinting at untold connections and pathways that beckon exploration.",
  "question": "What hunger drives your artistic aspirations beyond visual forms?",
  "overlayLines": [
    "Art demands more than sight",
    "Paths intertwine through desire",
    "Hungry for connection",
    "Shapes pulse with intent"
  ],
  "backgroundElements": [
    {
      "type": "block",
      "x": 92.63,
      "y": 71.59,
      "size": 19.61,
      "blur": 6.85,
      "opacity": 0.63,
      "rotate": -38.87
    },
    {
      "type": "orb",
      "x": 40.53,
      "y": 8.63,
      "size": 37.22,
      "blur": 3.6,
      "opacity": 0.49,
      "rotate": 0.31
    },
    {
      "type": "bar",
      "x": 77.16,
      "y": 89.1,
      "size": 39.15,
      "blur": 3.96,
      "opacity": 0.58,
      "rotate": 38.72
    },
    {
      "type": "diamond",
      "x": 86.9,
      "y": 0,
      "size": 15.35,
      "blur": 5.78,
      "opacity": 0.35,
      "rotate": -13.18
    },
    {
      "type": "ring",
      "x": 24.98,
      "y": 50.8,
      "size": 25.04,
      "blur": 8.55,
      "opacity": 0.26,
      "rotate": -30.23
    },
    {
      "type": "block",
      "x": 50.76,
      "y": 83.37,
      "size": 35.76,
      "blur": 14.6,
      "opacity": 0.25,
      "rotate": 23.05
    },
    {
      "type": "orb",
      "x": 84.76,
      "y": 63.44,
      "size": 19.77,
      "blur": 15.07,
      "opacity": 0.42,
      "rotate": 24.09
    }
  ],
  "shapes": [
    {
      "x": 92.63,
      "y": 71.59,
      "size": 19.61,
      "blur": 6.85,
      "opacity": 0.63
    },
    {
      "x": 40.53,
      "y": 8.63,
      "size": 37.22,
      "blur": 3.6,
      "opacity": 0.49
    },
    {
      "x": 77.16,
      "y": 89.1,
      "size": 39.15,
      "blur": 3.96,
      "opacity": 0.58
    },
    {
      "x": 86.9,
      "y": 0,
      "size": 15.35,
      "blur": 5.78,
      "opacity": 0.35
    },
    {
      "x": 24.98,
      "y": 50.8,
      "size": 25.04,
      "blur": 8.55,
      "opacity": 0.26
    },
    {
      "x": 50.76,
      "y": 83.37,
      "size": 35.76,
      "blur": 14.6,
      "opacity": 0.25
    },
    {
      "x": 84.76,
      "y": 63.44,
      "size": 19.77,
      "blur": 15.07,
      "opacity": 0.42
    }
  ],
  "imagePath": "assets/generated/2026-04-03T00-00-00Z.png",
  "lobsterImagePath": "assets/lobsters/2026-04-03T00-00-00Z.png",
  "audioPath": "assets/audio/2026-04-03T00-00-00Z.mp3"
}
